CasambiBt/__init__.py
CasambiBt/_cache.py
CasambiBt/_casambi.py
CasambiBt/_client.py
CasambiBt/_constants.py
CasambiBt/_discover.py
CasambiBt/_encryption.py
CasambiBt/_keystore.py
CasambiBt/_network.py
CasambiBt/_operation.py
CasambiBt/_switch.py
CasambiBt/_unit.py
CasambiBt/errors.py
CasambiBt/py.typed
casambi_bt-0.3.0.dist-info/licenses/LICENSE
casambi_bt-0.3.0.dist-info/METADATA
casambi_bt-0.3.0.dist-info/WHEEL
casambi_bt-0.3.0.dist-info/top_level.txt
casambi_bt-0.3.0.dist-info/RECORD
