Metadata-Version: 2.4
Name: casambi-bt
Version: 0.3.0
Summary: A minimal, unofficial implementation of a bluetooth client for casambi devices
Home-page: https://github.com/lkempf/casambi-bt
Author: lkempf
Author-email: pypi@lukas-kempf.de
Classifier: Programming Language :: Python :: 3.12
Classifier: License :: OSI Approved :: Apache Software License
Classifier: Operating System :: OS Independent
Classifier: Development Status :: 4 - Beta
Requires-Python: >=3.11
License-File: LICENSE
Requires-Dist: bleak<2.0.0,>=0.22
Requires-Dist: cryptography>=40.0.0
Requires-Dist: httpx>=0.25
Requires-Dist: bleak_retry_connector>=3.6.0
Requires-Dist: aiopath==0.7.*
Dynamic: license-file
